melty/__init__.py
melty/example.py
melty-0.0.1.dist-info/METADATA
melty-0.0.1.dist-info/WHEEL
melty-0.0.1.dist-info/licenses/LICENSE
melty-0.0.1.dist-info/RECORD
